makana_service/__init__.py
makana_service/_version.py
makana_service/labextension/package.json
makana_service/labextension/static/568.b0e72dd5fbbd07d5cafc.js
makana_service/labextension/static/747.6dcc7c39436e4d69b08f.js
makana_service/labextension/static/remoteEntry.883405819d538dca6f8d.js
makana_service/labextension/static/style.js
makana_service/labextension/static/third-party-licenses.json
makana_service/nbextension/README.md
makana_service/nbextension/jupytext_menu.png
makana_service/nbextension/main.css
makana_service/nbextension/main.js
makana_service/nbextension/maknaservice.yml
makana_service-0.1.3.data/data/etc/jupyter/jupyter_notebook_config.d/makana_service.json
makana_service-0.1.3.data/data/etc/jupyter/jupyter_server_config.d/makana_service.json
makana_service-0.1.3.data/data/etc/jupyter/nbconfig/notebook.d/makana_service.json
makana_service-0.1.3.data/data/share/jupyter/nbextensions/makana_service/README.md
makana_service-0.1.3.data/data/share/jupyter/nbextensions/makana_service/jupytext_menu.png
makana_service-0.1.3.data/data/share/jupyter/nbextensions/makana_service/main.js
makana_service-0.1.3.data/data/share/jupyter/nbextensions/makana_service/maknaservice.yml
makana_service-0.1.3.dist-info/LICENSE
makana_service-0.1.3.dist-info/METADATA
makana_service-0.1.3.dist-info/WHEEL
makana_service-0.1.3.dist-info/top_level.txt
makana_service-0.1.3.dist-info/RECORD
